datalake_copy/__init__.py
datalake_copy/artifact_store.py
datalake_copy-0.1.dist-info/METADATA
datalake_copy-0.1.dist-info/WHEEL
datalake_copy-0.1.dist-info/top_level.txt
datalake_copy-0.1.dist-info/RECORD
