Metadata-Version: 2.1
Name: datalake-copy
Version: 0.1
Summary: A library for datalake copying to databricks
Author: Eric Schles
Requires-Dist: requests
